pgzpro/__init__.py
pgzpro/core.py
pgzpro/exceptions.py
pgzpro/generator.py
pgzpro/notifications.py
pgzpro/utils.py
pgzpro-1.1.1.dist-info/METADATA
pgzpro-1.1.1.dist-info/WHEEL
pgzpro-1.1.1.dist-info/top_level.txt
pgzpro-1.1.1.dist-info/RECORD
