Metadata-Version: 2.4
Name: pgzpro
Version: 1.1.1
Summary: A powerful Python library that combines AI image generation with Pygame Zero enhancements. Create stunning games with AI-generated assets and streamlined development workflow.
Author-email: Georgii Nikishov <georgiinikishov@yandex.ru>
License: MIT
Keywords: pygame,pgzero,pgzpro,pgzhelper
Classifier: Development Status :: 3 - Alpha
Classifier: Intended Audience :: Developers
Classifier: License :: OSI Approved :: MIT License
Classifier: Programming Language :: Python :: 3
Classifier: Programming Language :: Python :: 3.8
Classifier: Programming Language :: Python :: 3.9
Classifier: Programming Language :: Python :: 3.10
Classifier: Programming Language :: Python :: 3.11
Requires-Dist: g4f
Requires-Dist: pgzero
Requires-Dist: deep_translator
Requires-Dist: pillow
Requires-Dist: screeninfo
